timestampprocessing/__init__.py
timestampprocessing/timestampprocessing.py
TimeStampProcessing-0.3.2.dist-info/METADATA
TimeStampProcessing-0.3.2.dist-info/WHEEL
TimeStampProcessing-0.3.2.dist-info/top_level.txt
TimeStampProcessing-0.3.2.dist-info/RECORD
