Metadata-Version: 2.1
Name: TimeStampProcessing
Version: 0.3.2
Summary: A package for timestamp-related data processing
Home-page: http://github.com/yourusername/TimeStampProcessing
Author: Wei Wang
Author-email: wwang487@wisc.edu
License: MIT
Platform: UNKNOWN
Classifier: Programming Language :: Python :: 3
Classifier: License :: OSI Approved :: MIT License
Classifier: Operating System :: OS Independent
Requires-Python: >=3.6
Requires-Dist: setuptools
Requires-Dist: pytest
Requires-Dist: numpy
Requires-Dist: pandas
Requires-Dist: scipy
Requires-Dist: pytz
Requires-Dist: astral
